{"nodes": [{"id": "d_ai_ontology_platform_hermes_skill_md", "label": "SKILL.md", "file_type": "document", "source_file": ".hermes/SKILL.md", "source_location": "L1"}, {"id": "hermes_skill_ontology_platform_best_practices", "label": "ontology-platform Best Practices", "file_type": "document", "source_file": ".hermes/SKILL.md", "source_location": "L8"}, {"id": "hermes_skill_\u6587\u6863\u516d\u5c42\u95ed\u73af", "label": "\u6587\u6863\u516d\u5c42\u95ed\u73af", "file_type": "document", "source_file": ".hermes/SKILL.md", "source_location": "L10"}, {"id": "hermes_skill_ddd_\u5206\u5c42\u67b6\u6784", "label": "DDD \u5206\u5c42\u67b6\u6784", "file_type": "document", "source_file": ".hermes/SKILL.md", "source_location": "L23"}, {"id": "hermes_skill_\u53cc\u6a21\u5757\u67b6\u6784", "label": "\u53cc\u6a21\u5757\u67b6\u6784", "file_type": "document", "source_file": ".hermes/SKILL.md", "source_location": "L36"}, {"id": "hermes_skill_\u6d4b\u8bd5\u5206\u5c42", "label": "\u6d4b\u8bd5\u5206\u5c42", "file_type": "document", "source_file": ".hermes/SKILL.md", "source_location": "L47"}, {"id": "hermes_skill_\u6587\u6863\u8def\u5f84", "label": "\u6587\u6863\u8def\u5f84", "file_type": "document", "source_file": ".hermes/SKILL.md", "source_location": "L57"}, {"id": "hermes_skill_\u5e38\u89c1_pitfalls", "label": "\u5e38\u89c1 Pitfalls", "file_type": "document", "source_file": ".hermes/SKILL.md", "source_location": "L67"}, {"id": "hermes_skill_\u542f\u52a8\u6d41\u7a0b", "label": "\u542f\u52a8\u6d41\u7a0b", "file_type": "document", "source_file": ".hermes/SKILL.md", "source_location": "L75"}], "edges": [{"source": "d_ai_ontology_platform_hermes_skill_md", "target": "hermes_skill_ontology_platform_best_practices", "relation": "contains", "confidence": "EXTRACTED", "source_file": ".hermes/SKILL.md", "source_location": "L8", "weight": 1.0}, {"source": "hermes_skill_ontology_platform_best_practices", "target": "hermes_skill_\u6587\u6863\u516d\u5c42\u95ed\u73af", "relation": "contains", "confidence": "EXTRACTED", "source_file": ".hermes/SKILL.md", "source_location": "L10", "weight": 1.0}, {"source": "hermes_skill_ontology_platform_best_practices", "target": "hermes_skill_ddd_\u5206\u5c42\u67b6\u6784", "relation": "contains", "confidence": "EXTRACTED", "source_file": ".hermes/SKILL.md", "source_location": "L23", "weight": 1.0}, {"source": "hermes_skill_ontology_platform_best_practices", "target": "hermes_skill_\u53cc\u6a21\u5757\u67b6\u6784", "relation": "contains", "confidence": "EXTRACTED", "source_file": ".hermes/SKILL.md", "source_location": "L36", "weight": 1.0}, {"source": "hermes_skill_ontology_platform_best_practices", "target": "hermes_skill_\u6d4b\u8bd5\u5206\u5c42", "relation": "contains", "confidence": "EXTRACTED", "source_file": ".hermes/SKILL.md", "source_location": "L47", "weight": 1.0}, {"source": "hermes_skill_ontology_platform_best_practices", "target": "hermes_skill_\u6587\u6863\u8def\u5f84", "relation": "contains", "confidence": "EXTRACTED", "source_file": ".hermes/SKILL.md", "source_location": "L57", "weight": 1.0}, {"source": "hermes_skill_ontology_platform_best_practices", "target": "hermes_skill_\u5e38\u89c1_pitfalls", "relation": "contains", "confidence": "EXTRACTED", "source_file": ".hermes/SKILL.md", "source_location": "L67", "weight": 1.0}, {"source": "hermes_skill_ontology_platform_best_practices", "target": "hermes_skill_\u542f\u52a8\u6d41\u7a0b", "relation": "contains", "confidence": "EXTRACTED", "source_file": ".hermes/SKILL.md", "source_location": "L75", "weight": 1.0}], "input_tokens": 0, "output_tokens": 0}