{"nodes": [{"id": "visual_color_scheme", "label": "\u8272\u5f69\u4f53\u7cfb\uff08#22A699\u7b49\uff09", "file_type": "document", "source_file": "\u89c6\u89c9\u8bc4\u4f30\u62a5\u544a.md", "source_location": null, "source_url": null, "captured_at": null, "author": null, "contributor": null}, {"id": "visual_typography", "label": "\u5b57\u4f53\u4f53\u7cfb\uff08Arial\uff09", "file_type": "document", "source_file": "\u89c6\u89c9\u8bc4\u4f30\u62a5\u544a.md", "source_location": null, "source_url": null, "captured_at": null, "author": null, "contributor": null}, {"id": "visual_layout", "label": "\u5e03\u5c40\u4e0e\u95f4\u8ddd", "file_type": "document", "source_file": "\u89c6\u89c9\u8bc4\u4f30\u62a5\u544a.md", "source_location": null, "source_url": null, "captured_at": null, "author": null, "contributor": null}, {"id": "visual_score", "label": "\u6574\u4f53\u8bc4\u5206 3.4/5", "file_type": "concept", "source_file": "\u89c6\u89c9\u8bc4\u4f30\u62a5\u544a.md", "source_location": null, "source_url": null, "captured_at": null, "author": null, "contributor": null}], "edges": [{"source": "visual_color_scheme", "target": "visual_score", "relation": "conceptually_related_to", "confidence": "INFERRED", "confidence_score": 0.8, "source_file": "\u89c6\u89c9\u8bc4\u4f30\u62a5\u544a.md", "source_location": "\u4e94", "weight": 1.0}, {"source": "visual_typography", "target": "visual_score", "relation": "conceptually_related_to", "confidence": "INFERRED", "confidence_score": 0.8, "source_file": "\u89c6\u89c9\u8bc4\u4f30\u62a5\u544a.md", "source_location": "\u4e94", "weight": 1.0}, {"source": "visual_layout", "target": "visual_score", "relation": "conceptually_related_to", "confidence": "INFERRED", "confidence_score": 0.8, "source_file": "\u89c6\u89c9\u8bc4\u4f30\u62a5\u544a.md", "source_location": "\u4e94", "weight": 1.0}, {"source": "visual_score", "target": "prd_ontology_platform", "relation": "references", "confidence": "INFERRED", "confidence_score": 0.9, "source_file": "\u89c6\u89c9\u8bc4\u4f30\u62a5\u544a.md", "source_location": "\u5168\u5c40\u6982\u89c8", "weight": 1.0}], "hyperedges": []}