{"nodes": [], "edges": [{"source": "onto_mcp_server", "target": "onto_springboot_backend", "relation": "references", "confidence": "EXTRACTED", "confidence_score": 1.0, "source_file": "mcp-server/README.md", "source_location": null, "weight": 1.0}, {"source": "onto_mcp_server", "target": "mcp_resolve_intent", "relation": "references", "confidence": "EXTRACTED", "confidence_score": 1.0, "source_file": "mcp-server/README.md", "source_location": null, "weight": 1.0}, {"source": "onto_mcp_server", "target": "mcp_query_ontology", "relation": "references", "confidence": "EXTRACTED", "confidence_score": 1.0, "source_file": "mcp-server/README.md", "source_location": null, "weight": 1.0}, {"source": "onto_mcp_server", "target": "mcp_traverse_graph", "relation": "references", "confidence": "EXTRACTED", "confidence_score": 1.0, "source_file": "mcp-server/README.md", "source_location": null, "weight": 1.0}, {"source": "onto_mcp_server", "target": "mcp_validate_instruction", "relation": "references", "confidence": "EXTRACTED", "confidence_score": 1.0, "source_file": "mcp-server/README.md", "source_location": null, "weight": 1.0}, {"source": "onto_mcp_server", "target": "mcp_execute_action", "relation": "references", "confidence": "EXTRACTED", "confidence_score": 1.0, "source_file": "mcp-server/README.md", "source_location": null, "weight": 1.0}], "hyperedges": []}